infer_parser/__init__.py
infer_parser/_parsers.py
infer_parser/_stubs.py
infer_parser/py.typed
infer_parser/test_infer_parser.py
infer_parser-0.1.2.dist-info/LICENSE
infer_parser-0.1.2.dist-info/METADATA
infer_parser-0.1.2.dist-info/WHEEL
infer_parser-0.1.2.dist-info/top_level.txt
infer_parser-0.1.2.dist-info/RECORD
