Metadata-Version: 2.1
Name: infer-parser
Version: 0.1.2
Summary: Make shell argument parsers from type hints
Home-page: https://github.com/lggruspe/infer-parser
Author: Levi Gruspe
Author-email: mail.levig@gmail.com
License: UNKNOWN
Platform: UNKNOWN
Classifier: Programming Language :: Python :: 3
Classifier: Programming Language :: Python :: 3.6
Classifier: Programming Language :: Python :: 3.7
Classifier: Programming Language :: Python :: 3.8
Classifier: Programming Language :: Python :: 3.9
Classifier: License :: OSI Approved :: MIT License
Requires-Python: >=3.6
